.gitignore
CHANGES.rst
MANIFEST.in
README.rst
setup.py
collective/__init__.py
collective.mcp.egg-info/PKG-INFO
collective.mcp.egg-info/SOURCES.txt
collective.mcp.egg-info/dependency_links.txt
collective.mcp.egg-info/entry_points.txt
collective.mcp.egg-info/namespace_packages.txt
collective.mcp.egg-info/not-zip-safe
collective.mcp.egg-info/requires.txt
collective.mcp.egg-info/top_level.txt
collective/mcp/__init__.py
collective/mcp/category.py
collective/mcp/configure.zcml
collective/mcp/rebuild_i18n.sh
collective/mcp/samples.zcml
collective/mcp/sorted_list.py
collective/mcp/browser/__init__.py
collective/mcp/browser/configure.zcml
collective/mcp/browser/control_panel.py
collective/mcp/browser/control_panel_page.py
collective/mcp/browser/templates/control_panel.pt
collective/mcp/doc/defect.rst
collective/mcp/doc/main.rst
collective/mcp/doc/modes.rst
collective/mcp/doc/multiobjects.rst
collective/mcp/doc/restriction.rst
collective/mcp/doc/theming.rst
collective/mcp/locales/collective.mcp.pot
collective/mcp/locales/manual.pot
collective/mcp/locales/fr/LC_MESSAGES/collective.mcp.mo
collective/mcp/locales/fr/LC_MESSAGES/collective.mcp.po
collective/mcp/locales/nl/LC_MESSAGES/collective.mcp.mo
collective/mcp/locales/nl/LC_MESSAGES/collective.mcp.po
collective/mcp/profiles/default/cssregistry.xml
collective/mcp/profiles/default/skins.xml
collective/mcp/samples/__init__.py
collective/mcp/samples/configure.zcml
collective/mcp/samples/defect.py
collective/mcp/samples/display_button.png
collective/mcp/samples/home.png
collective/mcp/samples/home_message.pt
collective/mcp/samples/home_message.py
collective/mcp/samples/notes.png
collective/mcp/samples/notes.pt
collective/mcp/samples/notes.py
collective/mcp/samples/notes_api.py
collective/mcp/samples/restricted.py
collective/mcp/skins/collective_mcp/mcp.css
collective/mcp/skins/collective_mcp/mcp_add_button.gif
collective/mcp/skins/collective_mcp/mcp_del_button.gif
collective/mcp/skins/collective_mcp/mcp_menu_default.png
collective/mcp/skins/collective_mcp/mcp_menu_home_bg.gif
collective/mcp/skins/collective_mcp/mcp_menu_home_hover_bg.gif
collective/mcp/skins/collective_mcp/mcp_menu_sep_bg.gif
collective/mcp/tests/__init__.py
collective/mcp/tests/coverage.txt
collective/mcp/tests/sorted_list.txt
collective/mcp/tests/test_docs.py
