Metadata-Version: 1.1
Name: collective.mcp
Version: 0.5
Summary: Macish Control Panel for Plone.
Home-page: https://github.com/zestsoftware/collective.mcp
Author: Zest Software
Author-email: info@zestsoftware.nl
License: GPL
Keywords: mac control panel
Platform: UNKNOWN
Classifier: Framework :: Plone
Classifier: Framework :: Plone :: 3.3
Classifier: Programming Language :: Python
Classifier: Programming Language :: Python :: 2.4
